python_geth/__init__.py
python_geth/contract_interface.py
python_geth/node.py
python_geth/templates/__init__.py
python_geth/templates/genesis.json
python_geth/templates/truffle-config.txt
python_geth/tests/__init__.py
python_geth/tests/node_test.py
python_geth/tests/suite.py
python_geth/tests/templates_test.py
python_geth-1.7.54.dist-info/METADATA
python_geth-1.7.54.dist-info/WHEEL
python_geth-1.7.54.dist-info/top_level.txt
python_geth-1.7.54.dist-info/RECORD
