Metadata-Version: 2.1
Name: python-geth
Version: 1.7.54
Summary: Release of the unofficial python geth library
Home-page: https://github.com/macutko/py_geth
Author: macutko
Author-email: matusgallik008@gmail.com
License: UNKNOWN
Download-URL: https://github.com/macutko/py_geth/archive/4.0.0.tar.gz
Keywords: geth,pyGeth,blockchain,ethereum,py-solc,python solidity,python blockchain
Platform: UNKNOWN
Classifier: Programming Language :: Python :: 3.6
Classifier: License :: OSI Approved :: MIT License
Classifier: Operating System :: Microsoft :: Windows
Requires-Python: >=3.6,<4
Requires-Dist: web3 (>=5.12.0)
